slides_sound/__init__.py
slides_sound/notes.py
slides_sound/slides_util.py
slides_sound/soundgen.py
slides_sound/version.py
slides_sound-1.0.2.data/scripts/contact_sheet
slides_sound-1.0.2.data/scripts/list_soundfont
slides_sound-1.0.2.data/scripts/music
slides_sound-1.0.2.data/scripts/rotate_resize
slides_sound-1.0.2.data/scripts/slides
slides_sound-1.0.2.dist-info/LICENSE
slides_sound-1.0.2.dist-info/METADATA
slides_sound-1.0.2.dist-info/WHEEL
slides_sound-1.0.2.dist-info/top_level.txt
slides_sound-1.0.2.dist-info/RECORD
