Metadata-Version: 2.1
Name: slides-sound
Version: 1.0.2
Summary: Tools for creating slideshows from images with generated music
Home-page: http://github.com/jpfxgood/slides-sound
Author: James Goodwin
Author-email: slides-soundc@jlgoodwin.com
License: MIT
Keywords: music,slides,images
Classifier: Programming Language :: Python :: 3
Classifier: License :: OSI Approved :: MIT License
Classifier: Operating System :: OS Independent
Requires-Python: >=3.6
License-File: LICENSE
Requires-Dist: Pillow
Requires-Dist: pyfluidsynth
Requires-Dist: pyaudio
